{"indexes":[{"v":{"$numberInt":"2"},"key":{"_id":{"$numberInt":"1"}},"name":"_id_"},{"v":{"$numberInt":"2"},"key":{"userId":{"$numberInt":"1"}},"name":"userId_1","background":true},{"v":{"$numberInt":"2"},"key":{"offerId":{"$numberInt":"1"}},"name":"offerId_1","background":true},{"v":{"$numberInt":"2"},"key":{"userId":{"$numberInt":"1"},"offerId":{"$numberInt":"1"}},"name":"userId_1_offerId_1","background":true,"unique":true},{"v":{"$numberInt":"2"},"key":{"userId":{"$numberInt":"1"},"createdAt":{"$numberInt":"-1"}},"name":"userId_1_createdAt_-1","background":true},{"v":{"$numberInt":"2"},"key":{"notifyOnExpiry":{"$numberInt":"1"},"offer.validUntil":{"$numberInt":"1"}},"name":"notifyOnExpiry_1_offer.validUntil_1","background":true}],"uuid":"39c47f53740f4562898e353196f2fe6f","collectionName":"offerfavorites","type":"collection"}